README.txt
setup.cfg
setup.py
Chandler_HelloWorldPlugin.egg-info/PKG-INFO
Chandler_HelloWorldPlugin.egg-info/SOURCES.txt
Chandler_HelloWorldPlugin.egg-info/dependency_links.txt
Chandler_HelloWorldPlugin.egg-info/entry_points.txt
Chandler_HelloWorldPlugin.egg-info/top_level.txt
hello_world/__init__.py
hello_world/tests.py
