Metadata-Version: 1.0
Name: Chandler-HelloWorldPlugin
Version: 0.7
Summary: This is just an example plugin project
Home-page: UNKNOWN
Author: Phillip J. Eby
Author-email: pje@telecommunity.com
License: UNKNOWN
Platform: UNKNOWN
Classifier: Development Status :: 5 - Production/Stable
Classifier: Environment :: Plugins
Classifier: Framework :: Chandler
Classifier: Intended Audience :: Developers
Classifier: License :: OSI Approved :: Apache Software License
Classifier: Operating System :: OS Independent
Classifier: Programming Language :: Python
Classifier: Topic :: Office/Business :: Groupware
Classifier: Topic :: Software Development :: Documentation
